<odoo>
    <data>
        <template id="pur_purchase_order_inherit" inherit_id="account.report_invoice_document">

              <xpath expr="//th[@name='th_description']" position="after">
               <th name="th_barcode"><span>Reference</span></th>
               <th name="th_par"><span>Parcours</span></th>
               <th name="th_class"><span>Class</span></th>
               <th name="th_design"><span>Designation</span></th>
               <th name="th_nde"><span>N'De Billet</span></th>
               <th name="th_com"><span>Comission</span></th>
               <th name="th_puht"><span>P.U.HT</span></th>
               <th name="th_puttc"><span>P.U.TTc</span></th>
            </xpath>


            <xpath expr="//td[@name='account_invoice_line_name']" position="after">

                <td id="barcode">
                         <span t-field="line.reference_arti"/>
                </td>
                <td id="ref">
                         <span t-field="line.par_cours"/>
                </td>
                <td id="cllss">
                         <span t-field="line.class_a"/>
                </td>
                <td id="design">
                         <span t-field="line.design"/>
                </td>
                <td id="de_billet">
                         <span t-field="line.de_billet"/>
                </td>
                <td id="com">
                         <span t-field="line.com"/>
                </td>
                <td id="puht">
                         <span t-field="line.puht"/>
                </td>
                <td id="puttc">
                         <span t-field="line.puttc"/>
                </td>
            </xpath>
<!--            <xpath expr="//div[@id='total']" position="replace">-->
<!--                <div id="total" class="row">-->
<!--                            <div t-attf-class="#{'col-6' if report_type != 'html' else 'col-sm-7 col-md-6'} ml-auto">-->
<!--                                <table class="table table-sm" style="page-break-inside: avoid;">-->
<!--                                    <tr class="border-black o_subtotal" style="">-->
<!--                                        <td><strong>Subtotal</strong></td>-->
<!--                                        <td class="text-right">-->
<!--                                            <span t-field="o.amount_untaxed"/>-->
<!--                                        </td>-->
<!--                                    </tr>-->
<!--                                    <tr style="">-->
<!--                                        <td><strong>Cost</strong></td>-->
<!--                                        <td class="text-right">-->
<!--                                            <span t-field="o.cost"/>-->
<!--                                        </td>-->
<!--                                    </tr>-->
<!--                                    <t t-foreach="o.amount_by_group" t-as="amount_by_group">-->
<!--                                        <tr style="">-->
<!--                                            <t t-if="len(o.line_ids.filtered(lambda line: line.tax_line_id)) in [0, 1] and float_compare(o.amount_untaxed, amount_by_group[2], precision_rounding=o.currency_id.rounding) == 0">-->
<!--                                                <td><span class="text-nowrap" t-esc="amount_by_group[0]"/></td>-->
<!--                                                <td class="text-right o_price_total">-->
<!--                                                    <span class="text-nowrap" t-esc="amount_by_group[3]"/>-->
<!--                                                </td>-->
<!--                                            </t>-->
<!--                                            <t t-else="">-->
<!--                                                <td>-->
<!--                                                    <span t-esc="amount_by_group[0]"/>-->
<!--                                                    <span class="text-nowrap"> on-->
<!--                                                        <t t-esc="amount_by_group[4]"/>-->
<!--                                                    </span>-->
<!--                                                </td>-->
<!--                                                <td class="text-right o_price_total">-->
<!--                                                    <span class="text-nowrap" t-esc="amount_by_group[3]"/>-->
<!--                                                </td>-->
<!--                                            </t>-->
<!--                                        </tr>-->
<!--                                    </t>-->
<!--                                    <tr class="border-black o_total">-->
<!--                                        <td><strong>Total</strong></td>-->
<!--                                        <td class="text-right">-->
<!--                                            <span class="text-nowrap" t-field="o.amount_total"/>-->
<!--                                        </td>-->
<!--                                    </tr>-->
<!--                                    <tr>-->
<!--                                        <td><strong>Margin</strong></td>-->
<!--                                        <td class="text-right">-->
<!--                                            <span class="text-nowrap" t-field="o.margin"/>-->
<!--                                        </td>-->
<!--                                    </tr>-->
<!--                                    <t t-if="print_with_payments">-->
<!--                                        <t t-if="o.payment_state != 'invoicing_legacy'">-->
<!--                                            <t t-set="payments_vals" t-value="o.sudo()._get_reconciled_info_JSON_values()"/>-->
<!--                                            <t t-foreach="payments_vals" t-as="payment_vals">-->
<!--                                                <tr>-->
<!--                                                    <td>-->
<!--                                                        <i class="oe_form_field text-right oe_payment_label">Paid on <t t-esc="payment_vals['date']" t-options="{&quot;widget&quot;: &quot;date&quot;}"/></i>-->
<!--                                                    </td>-->
<!--                                                    <td class="text-right">-->
<!--                                                        <span t-esc="payment_vals['amount']" t-options="{&quot;widget&quot;: &quot;monetary&quot;, &quot;display_currency&quot;: o.currency_id}"/>-->
<!--                                                    </td>-->
<!--                                                </tr>-->
<!--                                            </t>-->
<!--                                            <t t-if="len(payments_vals) &gt; 0">-->
<!--                                                <tr class="border-black">-->
<!--                                                    <td><strong>Amount Due</strong></td>-->
<!--                                                    <td class="text-right">-->
<!--                                                        <span t-field="o.amount_residual"/>-->
<!--                                                    </td>-->
<!--                                                </tr>-->
<!--                                            </t>-->
<!--                                        </t>-->
<!--                                    </t>-->
<!--                                </table>-->
<!--                            </div>-->
<!--                        </div>-->
<!--            </xpath>-->

        </template>
    </data>
</odoo>